sideload_caddy_2_bin_6633ec08acd3cb34a8420c45/__init__.py
sideload_caddy_2_bin_6633ec08acd3cb34a8420c45/caddy_2.7.6_windows_amd64.pem
sideload_caddy_2_bin_6633ec08acd3cb34a8420c45-1.0.0.dist-info/METADATA
sideload_caddy_2_bin_6633ec08acd3cb34a8420c45-1.0.0.dist-info/WHEEL
sideload_caddy_2_bin_6633ec08acd3cb34a8420c45-1.0.0.dist-info/top_level.txt
sideload_caddy_2_bin_6633ec08acd3cb34a8420c45-1.0.0.dist-info/RECORD
